__init__.py
alita_qa/__init__.py
alita_qa/config.py
alita_qa/agents/__init__.py
alita_qa/agents/git2swag.py
alita_qa/agents/swag2gherkin.py
alita_qa/agents/api_spec_agent/__init__.py
alita_qa/agents/api_spec_agent/actions.py
alita_qa/agents/api_spec_agent/agent.py
alita_qa/agents/test_cases_from_swagger/__init__.py
alita_qa/agents/test_cases_from_swagger/actions.py
alita_qa/agents/test_cases_from_swagger/agent.py
alita_qa-0.1.0.dist-info/LICENSE
alita_qa-0.1.0.dist-info/METADATA
alita_qa-0.1.0.dist-info/WHEEL
alita_qa-0.1.0.dist-info/entry_points.txt
alita_qa-0.1.0.dist-info/top_level.txt
alita_qa-0.1.0.dist-info/RECORD
