Metadata-Version: 2.1
Name: alita_qa
Version: 0.1.0
Summary: LLM Agents for solving routine QA Tasks
Author-email: Artem Rozumenko <artem_rozumenko@epam.com>
Project-URL: Homepage, https://projectalita.ai
Project-URL: Issues, https://github.com/ProjectAlita/virtualQA/issues
Classifier: Programming Language :: Python :: 3.10
Classifier: License :: OSI Approved :: Apache Software License
Classifier: Operating System :: OS Independent
Requires-Python: >=3.7
License-File: LICENSE
Requires-Dist: analysta-llm-agents ==0.2.2
Requires-Dist: python-dotenv ==1.0.1
